atsphinx/toybox/__init__.py
atsphinx/toybox/utils.py
atsphinx/toybox/lindera_search/__init__.py
atsphinx/toybox/pyproject/__init__.py
atsphinx/toybox/sass/.gitignore
atsphinx/toybox/sass/__init__.py
atsphinx/toybox/sass/dart_sass.py
atsphinx/toybox/stlite/__init__.py
atsphinx/toybox/stlite/view.html.jinja
atsphinx/toybox/stlite/static/atsphinx-stlite.css
atsphinx_toybox-2025.1.21.dist-info/METADATA
atsphinx_toybox-2025.1.21.dist-info/WHEEL
atsphinx_toybox-2025.1.21.dist-info/licenses/LICENSE
atsphinx_toybox-2025.1.21.dist-info/RECORD
