Metadata-Version: 2.4
Name: atsphinx-toybox
Version: 2025.1.21
Summary: Miscellaneous sphinx-extension collection of attakei' trials.
Project-URL: Home, https://github.com/atsphinx/toybox
Project-URL: Documentation, https://atsphinx.github.io/toybox
Author-email: Kazuya Takei <myself@attakei.net>
License-Expression: Apache-2.0
License-File: LICENSE
Classifier: Development Status :: 3 - Alpha
Classifier: Framework :: Sphinx
Classifier: Framework :: Sphinx :: Extension
Classifier: Intended Audience :: Developers
Classifier: License :: OSI Approved :: Apache Software License
Classifier: Operating System :: OS Independent
Classifier: Programming Language :: Python
Classifier: Programming Language :: Python :: 3 :: Only
Classifier: Programming Language :: Python :: 3.9
Classifier: Programming Language :: Python :: 3.10
Classifier: Programming Language :: Python :: 3.11
Classifier: Programming Language :: Python :: 3.12
Classifier: Programming Language :: Python :: 3.13
Classifier: Topic :: Documentation
Classifier: Topic :: Documentation :: Sphinx
Classifier: Topic :: Software Development
Classifier: Topic :: Software Development :: Documentation
Classifier: Topic :: Software Development :: Libraries
Classifier: Topic :: Software Development :: Libraries :: Python Modules
Classifier: Topic :: Text Processing
Classifier: Topic :: Text Processing :: Markup
Classifier: Topic :: Text Processing :: Markup :: reStructuredText
Requires-Python: >=3.9
Requires-Dist: atsphinx-bulma>=0.2.0
Requires-Dist: sphinx
Provides-Extra: lindera-search
Requires-Dist: lindera-py>=0.38.4; extra == 'lindera-search'
Provides-Extra: sass
Requires-Dist: httpx>=0.28.0; extra == 'sass'
